README.rst
setup.py
kPAL.egg-info/PKG-INFO
kPAL.egg-info/SOURCES.txt
kPAL.egg-info/dependency_links.txt
kPAL.egg-info/entry_points.txt
kPAL.egg-info/pbr.json
kPAL.egg-info/requires.txt
kPAL.egg-info/top_level.txt
kpal/__init__.py
kpal/kdistlib.py
kpal/klib.py
kpal/kmer.py
kpal/metrics.py
kpal/modality.py