Metadata-Version: 1.1
Name: kPAL
Version: 2.1.1
Summary: k-mer analysis toolkit and programming library.
Home-page: https://git.lumc.nl/j.f.j.laros/k-mer
Author: LUMC, Jeroen F.J. Laros, Martijn Vermaat
Author-email: J.F.J.Laros@lumc.nl
License: MIT License
Keywords: bioinformatics
Platform: any
Classifier: Development Status :: 3 - Alpha
Classifier: Intended Audience :: Science/Research
Classifier: Intended Audience :: Developers
Classifier: License :: OSI Approved :: MIT License
Classifier: Operating System :: OS Independent
Classifier: Programming Language :: Python
Classifier: Programming Language :: Python :: 2
Classifier: Programming Language :: Python :: 2.6
Classifier: Programming Language :: Python :: 2.7
Classifier: Programming Language :: Python :: 3
Classifier: Programming Language :: Python :: 3.3
Classifier: Programming Language :: Python :: 3.4
Classifier: Topic :: Scientific/Engineering :: Bio-Informatics
